fingpt/__init__.py
fingpt/FinGPT_Benchmark/__init__.py
fingpt/FinGPT_Benchmark/train_lora.py
fingpt/FinGPT_Benchmark/utils.py
fingpt/FinGPT_RAG/__init__.py
fingpt/FinGPT_v3/__init__.py
FinGPT-0.0.1.dist-info/LICENSE
FinGPT-0.0.1.dist-info/METADATA
FinGPT-0.0.1.dist-info/WHEEL
FinGPT-0.0.1.dist-info/top_level.txt
FinGPT-0.0.1.dist-info/RECORD
