Metadata-Version: 2.1
Name: FinGPT
Version: 0.0.1
Summary: FinGPT
Home-page: https://github.com/AI4Finance-Foundation/FinGPT
Author: Bruce Yang
Author-email: hy2500@columbia.edu
License: MIT
Keywords: Financial Large Language Models
Platform: any
Classifier: License :: OSI Approved :: MIT License
Classifier: Programming Language :: Python
Classifier: Programming Language :: Python :: 3
Classifier: Programming Language :: Python :: 3.6
Classifier: Programming Language :: Python :: 3.7
Classifier: Programming Language :: Python :: 3.8
Classifier: Programming Language :: Python :: Implementation :: CPython
Classifier: Programming Language :: Python :: Implementation :: PyPy
Requires-Python: >=3.6
License-File: LICENSE
